product_key_memory/__init__.py
product_key_memory/product_key_memory.py
product_key_memory/transformer.py
product_key_memory-0.2.11.dist-info/LICENSE
product_key_memory-0.2.11.dist-info/METADATA
product_key_memory-0.2.11.dist-info/WHEEL
product_key_memory-0.2.11.dist-info/top_level.txt
product_key_memory-0.2.11.dist-info/RECORD
