Metadata-Version: 2.1
Name: product_key_memory
Version: 0.2.11
Summary: Product Key Memory
Home-page: https://github.com/lucidrains/product-key-memory
Author: Aran Komatsuzaki, Phil Wang
Author-email: aran1234321@gmail.com, lucidrains@gmail.com
License: MIT
Keywords: transformers,artificial intelligence
Classifier: Development Status :: 4 - Beta
Classifier: Intended Audience :: Developers
Classifier: Topic :: Scientific/Engineering :: Artificial Intelligence
Classifier: License :: OSI Approved :: MIT License
Classifier: Programming Language :: Python :: 3.6
License-File: LICENSE
Requires-Dist: colt5-attention >=0.10.14
Requires-Dist: einops >=0.6
Requires-Dist: torch
